[
    {
        "name": "Microondas Midea",
        "description": "Horno microondas Midea, modelo EM720CXX, de 20 Litros de capacidad. Cuenta con 6 programas para calentar, descongelar o cocinar tu comida rápidamente y 11 niveles de potencia.",
        "cost": 94,
        "currency": "USD",
        "imgSrc": "img/10.jpg",
        "soldCount": 88,
        "id":10
    },
    {
        "name": "Heladera James frío seco Inverter",
        "description": "MODELO J 501 INV INOX: Descongelado y arranque totalmente automático, Congelado libre de escarcha (NO FROST), Sistema de enfriamiento rápido, Caja de vegetales, Estantes de cristal templado antiderrames, Amplio espacio en anaqueles, Gabinetes texturados",
        "cost": 908,
        "currency": "USD",
        "imgSrc": "img/11.jpg",
        "soldCount": 35,
        "id":11
    },
    {
        "name": "Lavarropas Inverter GENERAL ELECTRIC 10,2Kg",
        "description": "avarropas GE con capacidad para 10Kg. Cuenta con 14 programas de lavado incluído el programa night wash ultra silencioso y ECOlavado.",
        "cost": 657,
        "currency": "USD",
        "imgSrc": "img/32.jpg",
        "soldCount": 20,
        "id":32
    },
    {
        "name": "Smart TV SAMSUNG 50 Crystal 4K UHD Nuevo Modelo 2021",
        "description": "Disfrutá del contenido que más te gusta en la mejor calidad de imagen con este smart tv Samsung de 50 con resolución 4K UHD.",
        "cost": 769,
        "currency": "USD",
        "imgSrc": "img/33.jpg",
        "soldCount": 18,
        "id":33
    }
]
